dbt/tests/__about__.py
dbt/tests/adapter/aliases/fixtures.py
dbt/tests/adapter/aliases/test_aliases.py
dbt/tests/adapter/basic/__init__.py
dbt/tests/adapter/basic/expected_catalog.py
dbt/tests/adapter/basic/files.py
dbt/tests/adapter/basic/test_adapter_methods.py
dbt/tests/adapter/basic/test_base.py
dbt/tests/adapter/basic/test_docs_generate.py
dbt/tests/adapter/basic/test_empty.py
dbt/tests/adapter/basic/test_ephemeral.py
dbt/tests/adapter/basic/test_generic_tests.py
dbt/tests/adapter/basic/test_get_catalog_for_single_relation.py
dbt/tests/adapter/basic/test_incremental.py
dbt/tests/adapter/basic/test_singular_tests.py
dbt/tests/adapter/basic/test_singular_tests_ephemeral.py
dbt/tests/adapter/basic/test_snapshot_check_cols.py
dbt/tests/adapter/basic/test_snapshot_timestamp.py
dbt/tests/adapter/basic/test_table_materialization.py
dbt/tests/adapter/basic/test_validate_connection.py
dbt/tests/adapter/caching/test_caching.py
dbt/tests/adapter/catalog/files.py
dbt/tests/adapter/catalog/relation_types.py
dbt/tests/adapter/catalog_integrations/test_catalog_integration.py
dbt/tests/adapter/column_types/fixtures.py
dbt/tests/adapter/column_types/test_column_types.py
dbt/tests/adapter/concurrency/test_concurrency.py
dbt/tests/adapter/constraints/fixtures.py
dbt/tests/adapter/constraints/test_constraints.py
dbt/tests/adapter/dbt_clone/fixtures.py
dbt/tests/adapter/dbt_clone/test_dbt_clone.py
dbt/tests/adapter/dbt_debug/test_dbt_debug.py
dbt/tests/adapter/dbt_show/fixtures.py
dbt/tests/adapter/dbt_show/test_dbt_show.py
dbt/tests/adapter/empty/_models.py
dbt/tests/adapter/empty/test_empty.py
dbt/tests/adapter/ephemeral/test_ephemeral.py
dbt/tests/adapter/functions/files.py
dbt/tests/adapter/functions/test_udafs.py
dbt/tests/adapter/functions/test_udfs.py
dbt/tests/adapter/grants/base_grants.py
dbt/tests/adapter/grants/test_incremental_grants.py
dbt/tests/adapter/grants/test_invalid_grants.py
dbt/tests/adapter/grants/test_model_grants.py
dbt_tests_adapter-1.19.6.dist-info/METADATA
dbt_tests_adapter-1.19.6.dist-info/WHEEL
dbt_tests_adapter-1.19.6.dist-info/licenses/LICENSE
dbt_tests_adapter-1.19.6.dist-info/RECORD
