Metadata-Version: 2.4
Name: dbt-tests-adapter
Version: 1.19.6
Summary: The set of reusable tests and test fixtures used to test common functionality
Project-URL: Homepage, https://github.com/dbt-labs/dbt-adapters/tree/main/dbt-tests-adapter
Project-URL: Documentation, https://docs.getdbt.com
Project-URL: Repository, https://github.com/dbt-labs/dbt-adapters.git#subdirectory=dbt-tests-adapter
Project-URL: Issues, https://github.com/dbt-labs/dbt-adapters/issues
Project-URL: Changelog, https://github.com/dbt-labs/dbt-adapters/blob/main/dbt-tests-adapter/CHANGELOG.md
Author-email: dbt Labs <info@dbtlabs.com>
Maintainer-email: dbt Labs <info@dbtlabs.com>
License-File: LICENSE
Keywords: adapter,adapters,database,dbt,dbt Cloud,dbt Core,dbt Labs,dbt-core,elt
Classifier: Development Status :: 5 - Production/Stable
Classifier: License :: OSI Approved :: Apache Software License
Classifier: Operating System :: MacOS :: MacOS X
Classifier: Operating System :: Microsoft :: Windows
Classifier: Operating System :: POSIX :: Linux
Classifier: Programming Language :: Python :: 3.10
Classifier: Programming Language :: Python :: 3.11
Classifier: Programming Language :: Python :: 3.12
Classifier: Programming Language :: Python :: 3.13
Requires-Python: >=3.10.0
Requires-Dist: dbt-adapters<2.0,>=1.14.0
Requires-Dist: dbt-common<2.0,>=1.34.0
Requires-Dist: dbt-core>=1.8.0a1
Requires-Dist: freezegun
Requires-Dist: pyyaml
